{"dependencies":[{"name":"/Volumes/WORK/GIT/17_CS_cityIO_Frontend/package.json","includedInParent":true,"mtime":1523925118628},{"name":"/Volumes/WORK/GIT/17_CS_cityIO_Frontend/node_modules/has/package.json","includedInParent":true,"mtime":1523925103498},{"name":"function-bind","loc":{"line":1,"column":19}}],"generated":{"js":"var bind = require('function-bind');\n\nmodule.exports = bind.call(Function.call, Object.prototype.hasOwnProperty);","map":{"mappings":[{"generated":{"line":1,"column":0},"source":"node_modules/has/src/index.js","original":{"line":1,"column":0}},{"name":"bind","generated":{"line":1,"column":4},"source":"node_modules/has/src/index.js","original":{"line":1,"column":4}},{"name":"require","generated":{"line":1,"column":11},"source":"node_modules/has/src/index.js","original":{"line":1,"column":11}},{"generated":{"line":1,"column":19},"source":"node_modules/has/src/index.js","original":{"line":1,"column":19}},{"generated":{"line":1,"column":34},"source":"node_modules/has/src/index.js","original":{"line":1,"column":11}},{"generated":{"line":1,"column":35},"source":"node_modules/has/src/index.js","original":{"line":1,"column":0}},{"name":"module","generated":{"line":3,"column":0},"source":"node_modules/has/src/index.js","original":{"line":3,"column":0}},{"name":"exports","generated":{"line":3,"column":7},"source":"node_modules/has/src/index.js","original":{"line":3,"column":7}},{"generated":{"line":3,"column":14},"source":"node_modules/has/src/index.js","original":{"line":3,"column":0}},{"name":"bind","generated":{"line":3,"column":17},"source":"node_modules/has/src/index.js","original":{"line":3,"column":17}},{"name":"call","generated":{"line":3,"column":22},"source":"node_modules/has/src/index.js","original":{"line":3,"column":22}},{"generated":{"line":3,"column":26},"source":"node_modules/has/src/index.js","original":{"line":3,"column":17}},{"name":"Function","generated":{"line":3,"column":27},"source":"node_modules/has/src/index.js","original":{"line":3,"column":27}},{"name":"call","generated":{"line":3,"column":36},"source":"node_modules/has/src/index.js","original":{"line":3,"column":36}},{"generated":{"line":3,"column":40},"source":"node_modules/has/src/index.js","original":{"line":3,"column":17}},{"name":"Object","generated":{"line":3,"column":42},"source":"node_modules/has/src/index.js","original":{"line":3,"column":42}},{"name":"prototype","generated":{"line":3,"column":49},"source":"node_modules/has/src/index.js","original":{"line":3,"column":49}},{"generated":{"line":3,"column":58},"source":"node_modules/has/src/index.js","original":{"line":3,"column":42}},{"name":"hasOwnProperty","generated":{"line":3,"column":59},"source":"node_modules/has/src/index.js","original":{"line":3,"column":59}},{"generated":{"line":3,"column":73},"source":"node_modules/has/src/index.js","original":{"line":3,"column":17}},{"generated":{"line":3,"column":74},"source":"node_modules/has/src/index.js","original":{"line":3,"column":0}}],"sources":{"node_modules/has/src/index.js":"var bind = require('function-bind');\n\nmodule.exports = bind.call(Function.call, Object.prototype.hasOwnProperty);\n"},"lineCount":null}},"hash":"62af4102e2b85ee96724c28f05725706","cacheData":{"env":{}}}